RealEstateApp
