Metadata-Version: 2.1
Name: RealEstateAppRealitica
Version: 0.2
Summary: Script that runs a web scraper in a background and gets all available real estates in Balkan area, and filters them by given parameters(country, city, municipality).
Home-page: https://github.com/urosjevremovic/Real-estate-app
Author: Uros Jevremovic
Author-email: jevremovic.uros91@gmail.com
License: MIT
Platform: UNKNOWN
